fuckpythonconfig/__init__.py
fuckpythonconfig/core.py
fuckpythonconfig/exceptions.py
fuckpythonconfig/utils.py
fuckpythonconfig-1.0.1.dist-info/METADATA
fuckpythonconfig-1.0.1.dist-info/WHEEL
fuckpythonconfig-1.0.1.dist-info/licenses/LICENSE
fuckpythonconfig-1.0.1.dist-info/RECORD
