Metadata-Version: 2.4
Name: fuckpythonconfig
Version: 1.0.1
Summary: Zero-boilerplate config loader: auto-discover TOML & .env, resolve ${VAR} and ${VAR:default}.
Project-URL: homepage, https://github.com/JGG0sbp66/fuckPythonConfig
Author: JGG0sbp66
License: MIT License
License-File: LICENSE
Keywords: config,dotenv,environment,python,toml
Classifier: Intended Audience :: Developers
Classifier: License :: OSI Approved :: MIT License
Classifier: Operating System :: OS Independent
Classifier: Programming Language :: Python :: 3
Classifier: Programming Language :: Python :: 3 :: Only
Classifier: Programming Language :: Python :: 3.11
Classifier: Programming Language :: Python :: 3.12
Classifier: Programming Language :: Python :: 3.13
Classifier: Topic :: Software Development :: Libraries
Requires-Python: >=3.11
Requires-Dist: python-dotenv>=1.1.1
